ai_safety_engine/__init__.py
ai_safety_engine/exceptions.py
ai_safety_engine/models.py
ai_safety_engine/base/__init__.py
ai_safety_engine/base/action_base.py
ai_safety_engine/base/policy.py
ai_safety_engine/base/rule_base.py
ai_safety_engine/llm/__init__.py
ai_safety_engine/llm/upsonic_llm.py
ai_safety_engine/policies/__init__.py
ai_safety_engine/policies/crypto_policies.py
ai_safety_engine/policies/phone_policies.py
ai_safety_engine-0.1.0.dist-info/METADATA
ai_safety_engine-0.1.0.dist-info/WHEEL
ai_safety_engine-0.1.0.dist-info/entry_points.txt
ai_safety_engine-0.1.0.dist-info/RECORD
