Metadata-Version: 2.4
Name: ai-safety-engine
Version: 0.1.0
Summary: Add your description here
Author-email: Onur ULUSOY <atadogan06@gmail.com>
Requires-Python: >=3.13
Requires-Dist: psycopg2-binary==2.9.10
Requires-Dist: sqlalchemy==2.0.43
Requires-Dist: upsonic==0.60.0a1754435135
